altrios/__init__.py
altrios/altrios_pyo3.cpython-311-x86_64-linux-gnu.so
altrios/altrios_pyo3.pyi
altrios/defaults.py
altrios/fuel_grid.py
altrios/metric_calculator.py
altrios/objectives.py
altrios/output_12072022.csv
altrios/plot.py
altrios/py.typed
altrios/rollout.py
altrios/sim_manager.py
altrios/stringline.py
altrios/stringline_old.py
altrios/user_interface.py
altrios/utilities.py
altrios/demos/.gitignore
altrios/demos/__init__.py
altrios/demos/bel_demo.py
altrios/demos/conv_demo.py
altrios/demos/demo_logging.py
altrios/demos/hel_demo.py
altrios/demos/rollout_demo.py
altrios/demos/set_speed_simple_corr_demo.py
altrios/demos/set_speed_train_sim_demo.py
altrios/demos/sim_manager_demo.py
altrios/demos/speed_limit_simple_corr_demo.py
altrios/demos/speed_limit_train_sim_demo.py
altrios/demos/test_demos.py
altrios/loaders/__init__.py
altrios/loaders/powertrain_components.py
altrios/optimization/__init__.py
altrios/optimization/cal_and_val.py
altrios/optimization/multi_obj_opt.py
altrios/resources/.gitignore
altrios/resources/Default Demand StoBar.csv
altrios/resources/Default Demand.csv
altrios/resources/TimedPaths.csv
altrios/resources/__init__.py
altrios/resources/powertrain_model_input_example.csv
altrios/resources/tpc_input_example.csv
altrios/resources/demo_data/README.md
altrios/resources/demo_data/link_path.csv
altrios/resources/demo_data/link_points_idx_simple_corridor.csv
altrios/resources/demo_data/speed_trace.csv
altrios/resources/demo_data/speed_trace_simple_corridor.csv
altrios/resources/demo_data/set_speed_train_sim_demo/to_dataframe_expected.csv
altrios/resources/demo_data/speed_limit_train_sim_demo/to_dataframe_expected.csv
altrios/resources/metrics_inputs/Cambium22_MidCase_annual_gea.csv
altrios/resources/metrics_inputs/Cambium22_MidCase_tod_gea.csv
altrios/resources/metrics_inputs/Cambium23_allScenarios_annual_gea.csv
altrios/resources/metrics_inputs/EIA_Electricity_Prices.csv
altrios-0.3.0.dist-info/METADATA
altrios-0.3.0.dist-info/WHEEL
altrios-0.3.0.dist-info/RECORD
altrios-0.3.0.dist-info/licenses/LICENSE.md
