Metadata-Version: 2.4
Name: altrios
Version: 0.3.0
Classifier: Programming Language :: Python :: 3
Classifier: License :: OSI Approved :: BSD License
Classifier: Operating System :: POSIX
Classifier: Operating System :: MacOS :: MacOS X
Classifier: Operating System :: Microsoft :: Windows
Requires-Dist: pandas>=2
Requires-Dist: numpy~=1.24
Requires-Dist: pymoo==0.6
Requires-Dist: openpyxl
Requires-Dist: xlrd
Requires-Dist: seaborn
Requires-Dist: matplotlib~=3.3
Requires-Dist: plotly~=6.0
Requires-Dist: typing-extensions
Requires-Dist: pyarrow>=16.0
Requires-Dist: polars==1.20.0
Requires-Dist: requests
Requires-Dist: pyyaml==6.0.2
Requires-Dist: simpy
Requires-Dist: msgpack==1.1.0
Requires-Dist: ipykernel~=6.29
Requires-Dist: executing~=2.0
Requires-Dist: pip
Requires-Dist: pytest~=8.3 ; extra == 'dev'
Requires-Dist: maturin~=1.8 ; extra == 'dev'
Requires-Dist: python-lsp-server~=1.10 ; extra == 'dev'
Requires-Dist: ruff~=0.9 ; extra == 'dev'
Requires-Dist: pylsp-mypy~=0.7.0 ; extra == 'dev'
Requires-Dist: memory-profiler~=0.61.0 ; extra == 'dev'
Provides-Extra: dev
License-File: LICENSE.md
Summary: Tool for modeling and optimization of advanced locomotive powertrains for freight rail decarbonization.
Home-Page: https://www.nrel.gov/transportation/altrios.html
Author: Chad Baker, Lead Developer, Nick Reinicke, Developer, Matt Bruchon, Developer, Saad Akhtar, Developer, Steven Shi, Developer, Jinghu Hu, Developer, Grant Payne, Developer, Jason Lustbader, PI, Garrett Anderson, Developer, Joel Allardyce, Developer, Prativa Hartnett, Developer, Steve Fritz, SwRI Lead, Tyler Dick, Co-PI
Author-email: ALTRIOS Team <altrios@nrel.gov>
License: BSD-3-Clause
Requires-Python: >=3.10, <3.12
Project-URL: homepage, https://www.nrel.gov/transportation/altrios.html
Project-URL: source, https://github.com/NREL/altrios
